Workbook
Name HSK: 'AALTO Korpi-Lagg'!$C$10
Name Personnel: Sheet2!$B$2:$B$6
Name YK: 'AALTO Korpi-Lagg'!$C$11

Sheet Budget TOTAL
B3: The Funding form for a Academy Project (www.aka.fi)
B5: Funding period starts: | C5: 1.1.2026 | D5: (dd.mm.yyyy) | F5: 3 years, starting from 1.1.2026
B6: Funding period ends: | C6: 31.12.2028 | D6: (dd.mm.yyyy)
G7: TOTAL BUDGET FOR THE CONSORTIUM
B8: Effective work hours | C8: 100 | D8: (%) | E8: = tehollinen työaika | G8: ONLY FOR TOTAL EVALUATION
G9: EACH PARTNER WILL FILL IN THEIR OWN BUDGET TO AoF PORTAL
B10: Indirect employee costs | C10: 46 | D10: (%) | E10: = HSK
B11: Overheads share | C11: 75 | D11: (%) | E11: = YK
B13: Other costs include VAT | C13: YES
B15: Salaries | C15: 2026 | E15: =C15+1 -> 2027 | G15: =E15+1 -> 2028 | I15: Total
A16: Choose from a list --> | B16: Postdoctoral Researcher | C16: ='AALTO Korpi-Lagg'!C16+'Budget (Partner 2)'!C16+'Budget (Partner 3)'!C16+'Budget (Partner 4)'!C16+'Budget (Partner 5)'!C16 -> 11 | D16: month(s) | E16: ='AALTO Korpi-Lagg'!E16+'Budget (Partner 2)'!E16+'Budget (Partner 3)'!E16+'Budget (Partner 4)'!E16+'Budget (Partner 5)'!E16 -> 11 | F16: month(s) | G16: ='AALTO Korpi-Lagg'!G16+'Budget (Partner 2)'!G16+'Budget (Partner 3)'!G16+'Budget (Partner 4)'!G16+'Budget (Partner 5)'!G16 -> 11 | H16: month(s) | K16: Max 11 months/year | M16: Make sure that a project starting/ending in the middle of a year has correct months
B17: name (optional, not in the form) | C17: 3800 | D17: €/month | E17: =IF(E16,ROUND(C17*1.02,0),0) -> 3876 | F17: €/month | G17: =IF(G16,ROUND(E17*1.02,0),0) -> 3954 | H17: €/month | I17: =ROUND(C16*C17+E16*E17+G16*G17,0) -> 127930 | M17: Fill in the monthly salary of the first year. The other years fill in automatically with an estimated raise (TES).
B19: Principal investigator | C19: ='AALTO Korpi-Lagg'!C19+'Budget (Partner 2)'!C19+'Budget (Partner 3)'!C19+'Budget (Partner 4)'!C19+'Budget (Partner 5)'!C19 -> 11 | D19: month(s) | E19: ='AALTO Korpi-Lagg'!E19+'Budget (Partner 2)'!E19+'Budget (Partner 3)'!E19+'Budget (Partner 4)'!E19+'Budget (Partner 5)'!E19 -> 11 | F19: month(s) | G19: ='AALTO Korpi-Lagg'!G19+'Budget (Partner 2)'!G19+'Budget (Partner 3)'!G19+'Budget (Partner 4)'!G19+'Budget (Partner 5)'!G19 -> 11 | H19: month(s)
B20: name (optional, not in the form) | C20: 3800 | D20: €/month | E20: =IF(E19,ROUND(C20*1.02,0),0) -> 3876 | F20: €/month | G20: =IF(G19,ROUND(E20*1.02,0),0) -> 3954 | H20: €/month | I20: =ROUND(C19*C20+E19*E20+G19*G20,0) -> 127930
B22: Postgraduate student | C22: ='AALTO Korpi-Lagg'!C22+'Budget (Partner 2)'!C22+'Budget (Partner 3)'!C22+'Budget (Partner 4)'!C22+'Budget (Partner 5)'!C22 -> 0 | D22: month(s) | E22: ='AALTO Korpi-Lagg'!E22+'Budget (Partner 2)'!E22+'Budget (Partner 3)'!E22+'Budget (Partner 4)'!E22+'Budget (Partner 5)'!E22 -> 0 | F22: month(s) | G22: ='AALTO Korpi-Lagg'!G22+'Budget (Partner 2)'!G22+'Budget (Partner 3)'!G22+'Budget (Partner 4)'!G22+'Budget (Partner 5)'!G22 -> 0 | H22: month(s)
B23: name (optional, not in the form) | C23: 0 | D23: €/month | E23: =IF(E22,ROUND(C23*1.02,0),0) -> 0 | F23: €/month | G23: =IF(G22,ROUND(E23*1.02,0),0) -> 0 | H23: €/month | I23: =ROUND(C22*C23+E22*E23+G22*G23,0) -> 0
B25: Postgraduate student | C25: ='AALTO Korpi-Lagg'!C25+'Budget (Partner 2)'!C25+'Budget (Partner 3)'!C25+'Budget (Partner 4)'!C25+'Budget (Partner 5)'!C25 -> 0 | D25: month(s) | E25: ='AALTO Korpi-Lagg'!E25+'Budget (Partner 2)'!E25+'Budget (Partner 3)'!E25+'Budget (Partner 4)'!E25+'Budget (Partner 5)'!E25 -> 0 | F25: month(s) | G25: ='AALTO Korpi-Lagg'!G25+'Budget (Partner 2)'!G25+'Budget (Partner 3)'!G25+'Budget (Partner 4)'!G25+'Budget (Partner 5)'!G25 -> 0 | H25: month(s)
B26: name (optional, not in the form) | C26: 0 | D26: €/month | E26: =IF(E25,ROUND(C26*1.02,0),0) -> 0 | F26: €/month | G26: =IF(G25,ROUND(E26*1.02,0),0) -> 0 | H26: €/month | I26: =ROUND(C25*C26+E25*E26+G25*G26,0) -> 0
B29: Salaries, total | C29: ='AALTO Korpi-Lagg'!C29+'Budget (Partner 2)'!C29+'Budget (Partner 3)'!C29+'Budget (Partner 4)'!C29+'Budget (Partner 5)'!C29 -> 80850 | E29: ='AALTO Korpi-Lagg'!E29+'Budget (Partner 2)'!E29+'Budget (Partner 3)'!E29+'Budget (Partner 4)'!E29+'Budget (Partner 5)'!E29 -> 82467 | G29: ='AALTO Korpi-Lagg'!G29+'Budget (Partner 2)'!G29+'Budget (Partner 3)'!G29+'Budget (Partner 4)'!G29+'Budget (Partner 5)'!G29 -> 84117 | I29: =SUM(C29:H29) -> 247434
B30: Indirect employee cost, total | C30: ='AALTO Korpi-Lagg'!C30+'Budget (Partner 2)'!C30+'Budget (Partner 3)'!C30+'Budget (Partner 4)'!C30+'Budget (Partner 5)'!C30 -> 37191 | E30: ='AALTO Korpi-Lagg'!E30+'Budget (Partner 2)'!E30+'Budget (Partner 3)'!E30+'Budget (Partner 4)'!E30+'Budget (Partner 5)'!E30 -> 37935 | G30: ='AALTO Korpi-Lagg'!G30+'Budget (Partner 2)'!G30+'Budget (Partner 3)'!G30+'Budget (Partner 4)'!G30+'Budget (Partner 5)'!G30 -> 38694 | I30: =SUM(C30:H30) -> 113820
B31: Total overheads share | C31: ='AALTO Korpi-Lagg'!C31+'Budget (Partner 2)'!C31+'Budget (Partner 3)'!C31+'Budget (Partner 4)'!C31+'Budget (Partner 5)'!C31 -> 88531 | E31: ='AALTO Korpi-Lagg'!E31+'Budget (Partner 2)'!E31+'Budget (Partner 3)'!E31+'Budget (Partner 4)'!E31+'Budget (Partner 5)'!E31 -> 90302 | G31: ='AALTO Korpi-Lagg'!G31+'Budget (Partner 2)'!G31+'Budget (Partner 3)'!G31+'Budget (Partner 4)'!G31+'Budget (Partner 5)'!G31 -> 92108 | I31: =SUM(C31:H31) -> 270941
B34: Other costs | C34: 2026 | E34: =C34+1 -> 2027 | G34: =E34+1 -> 2028 | I34: Total
B35: Materials | C35: ='AALTO Korpi-Lagg'!C35+'Budget (Partner 2)'!C35+'Budget (Partner 3)'!C35+'Budget (Partner 4)'!C35+'Budget (Partner 5)'!C35 -> 0 | E35: ='AALTO Korpi-Lagg'!E35+'Budget (Partner 2)'!E35+'Budget (Partner 3)'!E35+'Budget (Partner 4)'!E35+'Budget (Partner 5)'!E35 -> 0 | G35: ='AALTO Korpi-Lagg'!G35+'Budget (Partner 2)'!G35+'Budget (Partner 3)'!G35+'Budget (Partner 4)'!G35+'Budget (Partner 5)'!G35 -> 0 | I35: =ROUND(SUM(E35,C35,G35),0) -> 0
B36: Equipment | C36: ='AALTO Korpi-Lagg'!C36+'Budget (Partner 2)'!C36+'Budget (Partner 3)'!C36+'Budget (Partner 4)'!C36+'Budget (Partner 5)'!C36 -> 0 | E36: ='AALTO Korpi-Lagg'!E36+'Budget (Partner 2)'!E36+'Budget (Partner 3)'!E36+'Budget (Partner 4)'!E36+'Budget (Partner 5)'!E36 -> 0 | G36: ='AALTO Korpi-Lagg'!G36+'Budget (Partner 2)'!G36+'Budget (Partner 3)'!G36+'Budget (Partner 4)'!G36+'Budget (Partner 5)'!G36 -> 0 | I36: =ROUND(SUM(E36,C36,G36),0) -> 0
B37: Services | C37: ='AALTO Korpi-Lagg'!C37+'Budget (Partner 2)'!C37+'Budget (Partner 3)'!C37+'Budget (Partner 4)'!C37+'Budget (Partner 5)'!C37 -> 0 | E37: ='AALTO Korpi-Lagg'!E37+'Budget (Partner 2)'!E37+'Budget (Partner 3)'!E37+'Budget (Partner 4)'!E37+'Budget (Partner 5)'!E37 -> 0 | G37: ='AALTO Korpi-Lagg'!G37+'Budget (Partner 2)'!G37+'Budget (Partner 3)'!G37+'Budget (Partner 4)'!G37+'Budget (Partner 5)'!G37 -> 0 | I37: =ROUND(SUM(E37,C37,G37),0) -> 0
B38: Travel expenses | C38: ='AALTO Korpi-Lagg'!C38+'Budget (Partner 2)'!C38+'Budget (Partner 3)'!C38+'Budget (Partner 4)'!C38+'Budget (Partner 5)'!C38 -> 6000 | E38: ='AALTO Korpi-Lagg'!E38+'Budget (Partner 2)'!E38+'Budget (Partner 3)'!E38+'Budget (Partner 4)'!E38+'Budget (Partner 5)'!E38 -> 6000 | G38: ='AALTO Korpi-Lagg'!G38+'Budget (Partner 2)'!G38+'Budget (Partner 3)'!G38+'Budget (Partner 4)'!G38+'Budget (Partner 5)'!G38 -> 6000 | I38: =ROUND(SUM(E38,C38,G38),0) -> 18000
B39: Other costs | C39: ='AALTO Korpi-Lagg'!C39+'Budget (Partner 2)'!C39+'Budget (Partner 3)'!C39+'Budget (Partner 4)'!C39+'Budget (Partner 5)'!C39 -> 0 | E39: ='AALTO Korpi-Lagg'!E39+'Budget (Partner 2)'!E39+'Budget (Partner 3)'!E39+'Budget (Partner 4)'!E39+'Budget (Partner 5)'!E39 -> 0 | G39: ='AALTO Korpi-Lagg'!G39+'Budget (Partner 2)'!G39+'Budget (Partner 3)'!G39+'Budget (Partner 4)'!G39+'Budget (Partner 5)'!G39 -> 0 | I39: =ROUND(SUM(E39,C39,G39),0) -> 0
B40: Other costs, total | C40: =ROUND(SUM(C35:C39),0) -> 6000 | E40: =ROUND(SUM(E35:E39),0) -> 6000 | G40: =ROUND(SUM(G35:G39),0) -> 6000 | I40: =ROUND(SUM(E40,C40,G40),0) -> 18000
B42: Total costs | C42: =ROUND(C29+C30+C31+C40,0) -> 212572 | E42: =ROUND(E29+E30+E31+E40,0) -> 216704 | G42: =ROUND(G29+G30+G31+G40,0) -> 220919 | I42: =ROUND(SUM(E42,C42,G42),0) -> 650195
B46: Funding | C46: 2026 | E46: =C46+1 -> 2027 | G46: =E46+1 -> 2028 | I46: Total
B47: Own organisation | C47: =ROUND(C42*30%,0) -> 63772 | E47: =ROUND(E42*30%,0) -> 65011 | G47: =ROUND(G42*30%,0) -> 66276 | I47: =ROUND(SUM(E47,C47,G47),0) -> 195059 | J47: No. of partners:
B48: Foundation | C48: At our Department these are not used (except in very rare cases)
B49: Tekes
B50: Ministry
B51: EU
B52: Enterprise
B53: Other
B54: Other than Academy funding, total | C54: =C47 -> 63772 | E54: =E47 -> 65011 | G54: =G47 -> 66276 | I54: =ROUND(SUM(E54,C54,G54),0) -> 195059
B55: Funding contribution from other sources % | C55: =ROUND(C54*100/C42,0) -> 30 | E55: =ROUND(E54*100/E42,0) -> 30 | G55: =ROUND(G54*100/G42,0) -> 30 | I55: =ROUND(I54*100/I42,0) -> 30 | J55: 2
J56: AoF contr./partner: | M56: Funding: 6,5 million euros in total (HPC special call)
B57: Academy funding contribution € | C57: =C42-C54 -> 148800 | E57: =E42-E54 -> 151693 | G57: =G42-G54 -> 154643 | I57: =ROUND(SUM(E57,C57,G57),0) -> 455136 | J57: =I57/J55 -> 227568 | M57: up to €500,000 for individual project
B58: Academy funding contribution % | C58: =ROUND(C57*100/C42,0) -> 70 | E58: =ROUND(E57*100/E42,0) -> 70 | G58: =ROUND(G57*100/G42,0) -> 70 | I58: =ROUND(I57*100/I42,0) -> 70 | M58: up to €1,000,000 for a consortium, max €500,000 for a consortium member

Sheet AALTO Korpi-Lagg
B3: The Funding form for a Academy Project (www.aka.fi)
N4: Note that in the Academy system the separator is a period, not a comma!
B5: Funding period starts: | C5: 1.1.2026 | D5: (dd.mm.yyyy) | F5: 3 years, starting from 1.1.2026 | N5: (in this excel all figures are rounded to whole numbers)
B6: Funding period ends: | C6: 31.12.2028 | D6: (dd.mm.yyyy)
B8: Effective work hours | C8: 100 | D8: (%) | E8: = tehollinen työaika | O8: = areas to be filled in the online Academy form
B10: Indirect employee costs | C10: 46 | D10: (%) | E10: = HSK | N10: Funding: 6,5 million euros in total (HPC special call)
B11: Overheads share | C11: 75 | D11: (%) | E11: = YK | N11: up to €500,000 for individual project
N12: up to €1,000,000 for a consortium, max €500,000 for a consortium member
B13: Other costs include VAT | C13: YES
B15: Salaries | C15: 2026 | E15: =C15+1 -> 2027 | G15: =E15+1 -> 2028 | I15: Total
A16: Choose from a list --> | B16: Postdoctoral Researcher | C16: 11 | D16: month(s) | E16: 11 | F16: month(s) | G16: 11 | H16: month(s) | K16: Max 11 months/year | N16: Make sure that a project starting/ending in the middle of a year has correct months
B17: name (optional, not in the form) | C17: 4150 | D17: €/month | E17: =IF(E16,ROUND(C17*1.02,0),0) -> 4233 | F17: €/month | G17: =IF(G16,ROUND(E17*1.02,0),0) -> 4318 | H17: €/month | I17: =ROUND(C16*C17+E16*E17+G16*G17,0) -> 139711 | N17: Fill in the monthly salary of the first year. The other years fill in automatically with an estimated raise (TES).
B19: Postgraduate student | C19: 11 | D19: month(s) | E19: 11 | F19: month(s) | G19: 11 | H19: month(s)
B20: name (optional, not in the form) | C20: 3200 | D20: €/month | E20: =IF(E19,ROUND(C20*1.02,0),0) -> 3264 | F20: €/month | G20: =IF(G19,ROUND(E20*1.02,0),0) -> 3329 | H20: €/month | I20: =ROUND(C19*C20+E19*E20+G19*G20,0) -> 107723 | M20: For reference Department Salary table (round-up):
B22: Principal investigator | C22: 0 | D22: month(s) | E22: 0 | F22: month(s) | G22: 0 | H22: month(s) | M22: Doctoral student | P22: 3200 | Q22: €/month
B23: name (optional, not in the form) | C23: 7890 | D23: €/month | E23: =IF(E22,ROUND(C23*1.02,0),0) -> 0 | F23: €/month | G23: =IF(G22,ROUND(E23*1.02,0),0) -> 0 | H23: €/month | I23: =ROUND(C22*C23+E22*E23+G22*G23,0) -> 0 | M23: PostDoc | P23: 4150 | Q23: €/month
B25: Postgraduate student | C25: 0 | D25: month(s) | E25: 0 | F25: month(s) | G25: 0 | H25: month(s)
B26: name (optional, not in the form) | C26: 0 | D26: €/month | E26: =IF(E25,ROUND(C26*1.02,0),0) -> 0 | F26: €/month | G26: =IF(G25,ROUND(E26*1.02,0),0) -> 0 | H26: €/month | I26: =ROUND(C25*C26+E25*E26+G25*G26,0) -> 0
B29: Salaries, total | C29: =C16*C17+C19*C20+C22*C23+C25*C26 -> 80850 | E29: =E16*E17+E19*E20+E22*E23+E25*E26 -> 82467 | G29: =G16*G17+G19*G20+G22*G23+G25*G26 -> 84117 | I29: =SUM(C29:H29) -> 247434 | M29: Materials:
B30: Indirect employee cost, total | C30: =ROUND(C29*HSK%,0) -> 37191 | E30: =ROUND(E29*HSK%,0) -> 37935 | G30: =ROUND(G29*HSK%,0) -> 38694 | I30: =SUM(C30:H30) -> 113820 | M30: e.g. Research specific materials & small-scale equipment
B31: Total overheads share | C31: =ROUND((C29+C30)*YK%, 0) -> 88531 | E31: =ROUND((E29+E30)*YK%, 0) -> 90302 | G31: =ROUND((G29+G30)*YK%, 0) -> 92108 | I31: =SUM(C31:H31) -> 270941 | M31: (special computer for computing, special accessories,..),
M32: user experiment costs,..
B34: Other costs | C34: 2026 | E34: =C34+1 -> 2027 | G34: =E34+1 -> 2028 | I34: Total | M34: Equipment: | P34: Mobility:
B35: Materials | C35: 0 | E35: 0 | G35: 0 | I35: =ROUND(SUM(E35,C35,G35),0) -> 0 | M35: Only large-scale equipment (> 10 k€, service life > 3 years) | P35: AoF's Mobility Allowance changed into Mobility Aid.
B36: Equipment | C36: 0 | E36: 0 | G36: 0 | I36: =ROUND(SUM(E36,C36,G36),0) -> 0 | M36: Very rarely used at CS | P36: In Aalto this means that mobilty costs are covered as real costs.
B37: Services | C37: 0 | E37: 0 | G37: 0 | I37: =ROUND(SUM(E37,C37,G37),0) -> 0 | P37: These costs may be included:
B38: Travel expenses | C38: 6000 | E38: 6000 | G38: 6000 | I38: =ROUND(SUM(E38,C38,G38),0) -> 18000 | M38: Services: | P38: - flights etc.
B39: Other costs | C39: 0 | E39: 0 | G39: 0 | I39: =ROUND(SUM(E39,C39,G39),0) -> 0 | M39: NOTE!: AoF is part of Plan-S coalition and no longer accepts | P39: - moderate living expenses (examples provided on sheet Mobility)
B40: Other costs, total | C40: =ROUND(SUM(C35:C39),0) -> 6000 | E40: =ROUND(SUM(E35:E39),0) -> 6000 | G40: =ROUND(SUM(G35:G39),0) -> 6000 | I40: =ROUND(SUM(E40,C40,G40),0) -> 18000 | M40: Open Access publication fees as direct costs. | P40: - insurance
P41: - daily allowance (>1 months stays: 30%), Note: may be excluded if total budget is puffed up
B42: Total costs | C42: =ROUND(C29+C30+C31+C40,0) -> 212572 | E42: =ROUND(E29+E30+E31+E40,0) -> 216704 | G42: =ROUND(G29+G30+G31+G40,0) -> 220919 | I42: =ROUND(SUM(E42,C42,G42),0) -> 650195 | M42: Travel expenses: | P42: - family travel expenses (for > 12 months stays)
M43: Conferences etc. | P43: All budgeted under Travel expenses.
M44: + all costs related to mobility (see blue box). | P44: Note: Do not exaggerate, use moderation.
B46: Funding | C46: 2026 | E46: =C46+1 -> 2027 | G46: =E46+1 -> 2028 | I46: Total | M46: Other costs:
B47: Own organisation | C47: =ROUND(C42*30%,0) -> 63772 | E47: =ROUND(E42*30%,0) -> 65011 | G47: =ROUND(G42*30%,0) -> 66276 | I47: =ROUND(SUM(E47,C47,G47),0) -> 195059 | M47: e.g. personal grants
B48: Foundation | C48: At our Department these are not used (except in very rare cases) | M48: Grants for international guests (see Academy call text for further information)
B49: Tekes
B50: Ministry
B51: EU
B52: Enterprise
B53: Other
B54: Other than Academy funding, total | C54: =C47 -> 63772 | E54: =E47 -> 65011 | G54: =G47 -> 66276 | I54: =ROUND(SUM(E54,C54,G54),0) -> 195059
B55: Funding contribution from other sources % | C55: =ROUND(C54*100/C42,0) -> 30 | E55: =ROUND(E54*100/E42,0) -> 30 | G55: =ROUND(G54*100/G42,0) -> 30 | I55: =ROUND(I54*100/I42,0) -> 30
J56: max support:
B57: Academy funding contribution € | C57: =C42-C54 -> 148800 | E57: =E42-E54 -> 151693 | G57: =G42-G54 -> 154643 | I57: =ROUND(SUM(E57,C57,G57),0) -> 455136 | J57: 500000
B58: Academy funding contribution % | C58: =ROUND(C57*100/C42,0) -> 70 | E58: =ROUND(E57*100/E42,0) -> 70 | G58: =ROUND(G57*100/G42,0) -> 70 | I58: =ROUND(I57*100/I42,0) -> 70 | M58: This has to be max 70% (this sheet forces it to 70%) !!!
B60: Justification for the cost estimate: | C60: PhD student: a computer science PhD student. Postdoc: application domain science postdoctoral researcher | M60: Justify all research costs, itemised by type of expenditure, in the free-text field (max 2000 characters)
B63: Name of the person issuing commitment | C63: Casper Lassenius (casper.lassenius@aalto.fi) | J63: Do not change! Has to be the CS Vice Head of Research Casper Lassenius. Choose this text from the list (do not copy from here) !!

Sheet Budget (Partner 2)
B3: The Funding form for a Academy Project (www.aka.fi)
N4: Note that in the Academy system the separator is a period, not a comma!
B5: Funding period starts: | C5: 1.1.2026 | D5: (dd.mm.yyyy) | F5: 3 years, starting from 1.1.2026 | N5: (in this excel all figures are rounded to whole numbers)
B6: Funding period ends: | C6: 31.12.2028 | D6: (dd.mm.yyyy)
B8: Effective work hours | C8: 100 | D8: (%) | E8: = tehollinen työaika | O8: = areas to be filled in the online Academy form
B10: Indirect employee costs | C10: 46 | D10: (%) | E10: = HSK | N10: Funding: 6,5 million euros in total (HPC special call)
B11: Overheads share | C11: 75 | D11: (%) | E11: = YK | N11: up to €500,000 for individual project
N12: up to €1,000,000 for a consortium, max €500,000 for a consortium member
B13: Other costs include VAT | C13: YES
B15: Salaries | C15: 2026 | E15: =C15+1 -> 2027 | G15: =E15+1 -> 2028 | I15: Total
A16: Choose from a list --> | B16: Postdoctoral Researcher | C16: 0 | D16: month(s) | E16: 0 | F16: month(s) | G16: 0 | H16: month(s) | K16: Max 11 months/year | N16: Make sure that a project starting/ending in the middle of a year has correct months
B17: name (optional, not in the form) | C17: 4150 | D17: €/month | E17: =IF(E16,ROUND(C17*1.02,0),0) -> 0 | F17: €/month | G17: =IF(G16,ROUND(E17*1.02,0),0) -> 0 | H17: €/month | I17: =ROUND(C16*C17+E16*E17+G16*G17,0) -> 0 | N17: Fill in the monthly salary of the first year. The other years fill in automatically with an estimated raise (TES).
B19: Principal investigator | C19: 0 | D19: month(s) | E19: 0 | F19: month(s) | G19: 0 | H19: month(s)
B20: name (optional, not in the form) | C20: 3150 | D20: €/month | E20: =IF(E19,ROUND(C20*1.02,0),0) -> 0 | F20: €/month | G20: =IF(G19,ROUND(E20*1.02,0),0) -> 0 | H20: €/month | I20: =ROUND(C19*C20+E19*E20+G19*G20,0) -> 0
B22: Postgraduate student | C22: 0 | D22: month(s) | E22: 0 | F22: month(s) | G22: 0 | H22: month(s)
B23: name (optional, not in the form) | C23: 0 | D23: €/month | E23: =IF(E22,ROUND(C23*1.02,0),0) -> 0 | F23: €/month | G23: =IF(G22,ROUND(E23*1.02,0),0) -> 0 | H23: €/month | I23: =ROUND(C22*C23+E22*E23+G22*G23,0) -> 0
B25: Postgraduate student | C25: 0 | D25: month(s) | E25: 0 | F25: month(s) | G25: 0 | H25: month(s)
B26: name (optional, not in the form) | C26: 0 | D26: €/month | E26: =IF(E25,ROUND(C26*1.02,0),0) -> 0 | F26: €/month | G26: =IF(G25,ROUND(E26*1.02,0),0) -> 0 | H26: €/month | I26: =ROUND(C25*C26+E25*E26+G25*G26,0) -> 0
B29: Salaries, total | C29: =C16*C17+C19*C20+C22*C23+C25*C26 -> 0 | E29: =E16*E17+E19*E20+E22*E23+E25*E26 -> 0 | G29: =G16*G17+G19*G20+G22*G23+G25*G26 -> 0 | I29: =SUM(C29:H29) -> 0 | M29: Materials:
B30: Indirect employee cost, total | C30: =ROUND(C29*$C$10%,0) -> 0 | E30: =ROUND(E29*$C$10%,0) -> 0 | G30: =ROUND(G29*$C$10%,0) -> 0 | I30: =SUM(C30:H30) -> 0 | M30: e.g. Research specific materials & small-scale equipment
B31: Total overheads share | C31: =ROUND((C29+C30)*$C$11%, 0) -> 0 | E31: =ROUND((E29+E30)*$C$11%, 0) -> 0 | G31: =ROUND((G29+G30)*$C$11%, 0) -> 0 | I31: =SUM(C31:H31) -> 0 | M31: (special computer for computing, special accessories,..),
M32: user experiment costs,..
B34: Other costs | C34: 2026 | E34: =C34+1 -> 2027 | G34: =E34+1 -> 2028 | I34: Total | M34: Equipment: | P34: Mobility:
B35: Materials | C35: 0 | E35: 0 | G35: 0 | I35: =ROUND(SUM(E35,C35,G35),0) -> 0 | M35: Only large-scale equipment (> 10 k€, service life > 3 years) | P35: AoF's Mobility Allowance changed into Mobility Aid.
B36: Equipment | C36: 0 | E36: 0 | G36: 0 | I36: =ROUND(SUM(E36,C36,G36),0) -> 0 | M36: Very rarely used at CS | P36: In Aalto this means that mobilty costs are covered as real costs.
B37: Services | C37: 0 | E37: 0 | G37: 0 | I37: =ROUND(SUM(E37,C37,G37),0) -> 0 | P37: These costs may be included:
B38: Travel expenses | C38: 0 | E38: 0 | G38: 0 | I38: =ROUND(SUM(E38,C38,G38),0) -> 0 | M38: Services: | P38: - flights etc.
B39: Other costs | C39: 0 | E39: 0 | G39: 0 | I39: =ROUND(SUM(E39,C39,G39),0) -> 0 | M39: NOTE!: AoF is part of Plan-S coalition and no longer accepts | P39: - moderate living expenses (examples provided on sheet Mobility)
B40: Other costs, total | C40: =ROUND(SUM(C35:C39),0) -> 0 | E40: =ROUND(SUM(E35:E39),0) -> 0 | G40: =ROUND(SUM(G35:G39),0) -> 0 | I40: =ROUND(SUM(E40,C40,G40),0) -> 0 | M40: Open Access publication fees as direct costs. | P40: - insurance
P41: - daily allowance (>1 months stays: 30%), Note: may be excluded if total budget is puffed up
B42: Total costs | C42: =ROUND(C29+C30+C31+C40,0) -> 0 | E42: =ROUND(E29+E30+E31+E40,0) -> 0 | G42: =ROUND(G29+G30+G31+G40,0) -> 0 | I42: =ROUND(SUM(E42,C42,G42),0) -> 0 | M42: Travel expenses: | P42: - family travel expenses (for > 12 months stays)
M43: Conferences etc. | P43: All budgeted under Travel expenses.
M44: + all costs related to mobility (see blue box). | P44: Note: Do not exaggerate, use moderation.
B46: Funding | C46: 2026 | E46: =C46+1 -> 2027 | G46: =E46+1 -> 2028 | I46: Total | M46: Other costs:
B47: Own organisation | C47: =ROUND(C42*30%,0) -> 0 | E47: =ROUND(E42*30%,0) -> 0 | G47: =ROUND(G42*30%,0) -> 0 | I47: =ROUND(SUM(E47,C47,G47),0) -> 0 | M47: e.g. personal grants
B48: Foundation | C48: At our Department these are not used (except in very rare cases) | M48: Grants for international guests (see Academy call text for further information)
B49: Tekes
B50: Ministry
B51: EU
B52: Enterprise
B53: Other
B54: Other than Academy funding, total | C54: =C47 -> 0 | E54: =E47 -> 0 | G54: =G47 -> 0 | I54: =ROUND(SUM(E54,C54,G54),0) -> 0
B55: Funding contribution from other sources % | C55: =ROUND(C54*100/C42,0) -> #DIV/0! | E55: =ROUND(E54*100/E42,0) -> #DIV/0! | G55: =ROUND(G54*100/G42,0) -> #DIV/0! | I55: =ROUND(I54*100/I42,0) -> #DIV/0!
J56: max support:
B57: Academy funding contribution € | C57: =C42-C54 -> 0 | E57: =E42-E54 -> 0 | G57: =G42-G54 -> 0 | I57: =ROUND(SUM(E57,C57,G57),0) -> 0 | J57: 500000
B58: Academy funding contribution % | C58: =ROUND(C57*100/C42,0) -> #DIV/0! | E58: =ROUND(E57*100/E42,0) -> #DIV/0! | G58: =ROUND(G57*100/G42,0) -> #DIV/0! | I58: =ROUND(I57*100/I42,0) -> #DIV/0! | M58: This has to be max 70% (this sheet forces it to 70%) !!!
B60: Justification for the cost estimate: | M60: Justify all research costs, itemised by type of expenditure, in the free-text field (max 2000 characters)
B63: Name of the person issuing commitment

Sheet Budget (Partner 3)
B3: The Funding form for a Academy Project (www.aka.fi)
N4: Note that in the Academy system the separator is a period, not a comma!
B5: Funding period starts: | C5: 1.1.2026 | D5: (dd.mm.yyyy) | F5: 3 years, starting from 1.1.2026 | N5: (in this excel all figures are rounded to whole numbers)
B6: Funding period ends: | C6: 31.12.2028 | D6: (dd.mm.yyyy)
B8: Effective work hours | C8: 100 | D8: (%) | E8: = tehollinen työaika | O8: = areas to be filled in the online Academy form
B10: Indirect employee costs | C10: 46 | D10: (%) | E10: = HSK | N10: Funding: 6,5 million euros in total (HPC special call)
B11: Overheads share | C11: 75 | D11: (%) | E11: = YK | N11: up to €500,000 for individual project
B13: Other costs include VAT | C13: YES
B15: Salaries | C15: 2026 | E15: =C15+1 -> 2027 | G15: =E15+1 -> 2028 | I15: Total
A16: Choose from a list --> | B16: Postdoctoral Researcher | C16: 0 | D16: month(s) | E16: 0 | F16: month(s) | G16: 0 | H16: month(s) | K16: Max 11 months/year | N16: Make sure that a project starting/ending in the middle of a year has correct months
B17: name (optional, not in the form) | C17: 0 | D17: €/month | E17: =IF(E16,ROUND(C17*1.02,0),0) -> 0 | F17: €/month | G17: =IF(G16,ROUND(E17*1.02,0),0) -> 0 | H17: €/month | I17: =ROUND(C16*C17+E16*E17+G16*G17,0) -> 0 | N17: Fill in the monthly salary of the first year. The other years fill in automatically with an estimated raise (TES).
B19: Principal investigator | C19: 0 | D19: month(s) | E19: 0 | F19: month(s) | G19: 0 | H19: month(s)
B20: name (optional, not in the form) | C20: 0 | D20: €/month | E20: =IF(E19,ROUND(C20*1.02,0),0) -> 0 | F20: €/month | G20: =IF(G19,ROUND(E20*1.02,0),0) -> 0 | H20: €/month | I20: =ROUND(C19*C20+E19*E20+G19*G20,0) -> 0
B22: Postgraduate student | C22: 0 | D22: month(s) | E22: 0 | F22: month(s) | G22: 0 | H22: month(s)
B23: name (optional, not in the form) | C23: 0 | D23: €/month | E23: =IF(E22,ROUND(C23*1.02,0),0) -> 0 | F23: €/month | G23: =IF(G22,ROUND(E23*1.02,0),0) -> 0 | H23: €/month | I23: =ROUND(C22*C23+E22*E23+G22*G23,0) -> 0
B25: Postgraduate student | C25: 0 | D25: month(s) | E25: 0 | F25: month(s) | G25: 0 | H25: month(s)
B26: name (optional, not in the form) | C26: 0 | D26: €/month | E26: =IF(E25,ROUND(C26*1.02,0),0) -> 0 | F26: €/month | G26: =IF(G25,ROUND(E26*1.02,0),0) -> 0 | H26: €/month | I26: =ROUND(C25*C26+E25*E26+G25*G26,0) -> 0
B29: Salaries, total | C29: =C16*C17+C19*C20+C22*C23+C25*C26 -> 0 | E29: =E16*E17+E19*E20+E22*E23+E25*E26 -> 0 | G29: =G16*G17+G19*G20+G22*G23+G25*G26 -> 0 | I29: =SUM(C29:H29) -> 0 | M29: Materials:
B30: Indirect employee cost, total | C30: =ROUND(C29*$C$10%,0) -> 0 | E30: =ROUND(E29*$C$10%,0) -> 0 | G30: =ROUND(G29*$C$10%,0) -> 0 | I30: =SUM(C30:H30) -> 0 | M30: e.g. Research specific materials & small-scale equipment
B31: Total overheads share | C31: =ROUND((C29+C30)*$C$11%, 0) -> 0 | E31: =ROUND((E29+E30)*$C$11%, 0) -> 0 | G31: =ROUND((G29+G30)*$C$11%, 0) -> 0 | I31: =SUM(C31:H31) -> 0 | M31: (special computer for computing, special accessories,..),
M32: user experiment costs,..
B34: Other costs | C34: 2026 | E34: =C34+1 -> 2027 | G34: =E34+1 -> 2028 | I34: Total | M34: Equipment: | P34: Mobility:
B35: Materials | C35: 0 | E35: 0 | G35: 0 | I35: =ROUND(SUM(E35,C35,G35),0) -> 0 | M35: Only large-scale equipment (> 10 k€, service life > 3 years) | P35: AoF's Mobility Allowance changed into Mobility Aid.
B36: Equipment | C36: 0 | E36: 0 | G36: 0 | I36: =ROUND(SUM(E36,C36,G36),0) -> 0 | M36: Very rarely used at CS | P36: In Aalto this means that mobilty costs are covered as real costs.
B37: Services | C37: 0 | E37: 0 | G37: 0 | I37: =ROUND(SUM(E37,C37,G37),0) -> 0 | P37: These costs may be included:
B38: Travel expenses | C38: 0 | E38: 0 | G38: 0 | I38: =ROUND(SUM(E38,C38,G38),0) -> 0 | M38: Services: | P38: - flights etc.
B39: Other costs | C39: 0 | E39: 0 | G39: 0 | I39: =ROUND(SUM(E39,C39,G39),0) -> 0 | M39: NOTE!: AoF is part of Plan-S coalition and no longer accepts | P39: - moderate living expenses (examples provided on sheet Mobility)
B40: Other costs, total | C40: =ROUND(SUM(C35:C39),0) -> 0 | E40: =ROUND(SUM(E35:E39),0) -> 0 | G40: =ROUND(SUM(G35:G39),0) -> 0 | I40: =ROUND(SUM(E40,C40,G40),0) -> 0 | M40: Open Access publication fees as direct costs. | P40: - insurance
P41: - daily allowance (>1 months stays: 30%), Note: may be excluded if total budget is puffed up
B42: Total costs | C42: =ROUND(C29+C30+C31+C40,0) -> 0 | E42: =ROUND(E29+E30+E31+E40,0) -> 0 | G42: =ROUND(G29+G30+G31+G40,0) -> 0 | I42: =ROUND(SUM(E42,C42,G42),0) -> 0 | M42: Travel expenses: | P42: - family travel expenses (for > 12 months stays)
M43: Conferences etc. | P43: All budgeted under Travel expenses.
M44: + all costs related to mobility (see blue box). | P44: Note: Do not exaggerate, use moderation.
B46: Funding | C46: 2026 | E46: =C46+1 -> 2027 | G46: =E46+1 -> 2028 | I46: Total | M46: Other costs:
B47: Own organisation | C47: =ROUND(C42*30%,0) -> 0 | E47: =ROUND(E42*30%,0) -> 0 | G47: =ROUND(G42*30%,0) -> 0 | I47: =ROUND(SUM(E47,C47,G47),0) -> 0 | M47: e.g. personal grants
B48: Foundation | C48: At our Department these are not used (except in very rare cases) | M48: Grants for international guests (see Academy call text for further information)
B49: Tekes
B50: Ministry
B51: EU
B52: Enterprise
B53: Other
B54: Other than Academy funding, total | C54: =C47 -> 0 | E54: =E47 -> 0 | G54: =G47 -> 0 | I54: =ROUND(SUM(E54,C54,G54),0) -> 0
B55: Funding contribution from other sources % | C55: =ROUND(C54*100/C42,0) -> #DIV/0! | E55: =ROUND(E54*100/E42,0) -> #DIV/0! | G55: =ROUND(G54*100/G42,0) -> #DIV/0! | I55: =ROUND(I54*100/I42,0) -> #DIV/0!
J56: max support:
B57: Academy funding contribution € | C57: =C42-C54 -> 0 | E57: =E42-E54 -> 0 | G57: =G42-G54 -> 0 | I57: =ROUND(SUM(E57,C57,G57),0) -> 0 | J57: 500000
B58: Academy funding contribution % | C58: =ROUND(C57*100/C42,0) -> #DIV/0! | E58: =ROUND(E57*100/E42,0) -> #DIV/0! | G58: =ROUND(G57*100/G42,0) -> #DIV/0! | I58: =ROUND(I57*100/I42,0) -> #DIV/0! | M58: This has to be max 70% (this sheet forces it to 70%) !!!
B60: Justification for the cost estimate: | M60: Justify all research costs, itemised by type of expenditure, in the free-text field (max 2000 characters)
B63: Name of the person issuing commitment

Sheet Budget (Partner 4)
B3: The Funding form for a Academy Project (www.aka.fi)
N4: Note that in the Academy system the separator is a period, not a comma!
B5: Funding period starts: | C5: 1.1.2026 | D5: (dd.mm.yyyy) | F5: 3 years, starting from 1.1.2026 | N5: (in this excel all figures are rounded to whole numbers)
B6: Funding period ends: | C6: 31.12.2028 | D6: (dd.mm.yyyy)
B8: Effective work hours | C8: 100 | D8: (%) | E8: = tehollinen työaika | O8: = areas to be filled in the online Academy form
B10: Indirect employee costs | C10: 46 | D10: (%) | E10: = HSK | N10: Funding: 6,5 million euros in total (HPC special call)
B11: Overheads share | C11: 75 | D11: (%) | E11: = YK | N11: up to €500,000 for individual project
B13: Other costs include VAT | C13: YES
B15: Salaries | C15: 2026 | E15: =C15+1 -> 2027 | G15: =E15+1 -> 2028 | I15: Total
A16: Choose from a list --> | B16: Postdoctoral Researcher | C16: 0 | D16: month(s) | E16: 0 | F16: month(s) | G16: 0 | H16: month(s) | K16: Max 11 months/year | N16: Make sure that a project starting/ending in the middle of a year has correct months
B17: name (optional, not in the form) | C17: 0 | D17: €/month | E17: =IF(E16,ROUND(C17*1.02,0),0) -> 0 | F17: €/month | G17: =IF(G16,ROUND(E17*1.02,0),0) -> 0 | H17: €/month | I17: =ROUND(C16*C17+E16*E17+G16*G17,0) -> 0 | N17: Fill in the monthly salary of the first year. The other years fill in automatically with an estimated raise (TES).
B19: Principal investigator | C19: 0 | D19: month(s) | E19: 0 | F19: month(s) | G19: 0 | H19: month(s)
B20: name (optional, not in the form) | C20: 0 | D20: €/month | E20: =IF(E19,ROUND(C20*1.02,0),0) -> 0 | F20: €/month | G20: =IF(G19,ROUND(E20*1.02,0),0) -> 0 | H20: €/month | I20: =ROUND(C19*C20+E19*E20+G19*G20,0) -> 0
B22: Postgraduate student | C22: 0 | D22: month(s) | E22: 0 | F22: month(s) | G22: 0 | H22: month(s)
B23: name (optional, not in the form) | C23: 0 | D23: €/month | E23: =IF(E22,ROUND(C23*1.02,0),0) -> 0 | F23: €/month | G23: =IF(G22,ROUND(E23*1.02,0),0) -> 0 | H23: €/month | I23: =ROUND(C22*C23+E22*E23+G22*G23,0) -> 0
B25: Postgraduate student | C25: 0 | D25: month(s) | E25: 0 | F25: month(s) | G25: 0 | H25: month(s)
B26: name (optional, not in the form) | C26: 0 | D26: €/month | E26: =IF(E25,ROUND(C26*1.02,0),0) -> 0 | F26: €/month | G26: =IF(G25,ROUND(E26*1.02,0),0) -> 0 | H26: €/month | I26: =ROUND(C25*C26+E25*E26+G25*G26,0) -> 0
B29: Salaries, total | C29: =C16*C17+C19*C20+C22*C23+C25*C26 -> 0 | E29: =E16*E17+E19*E20+E22*E23+E25*E26 -> 0 | G29: =G16*G17+G19*G20+G22*G23+G25*G26 -> 0 | I29: =SUM(C29:H29) -> 0 | M29: Materials:
B30: Indirect employee cost, total | C30: =ROUND(C29*$C$10%,0) -> 0 | E30: =ROUND(E29*$C$10%,0) -> 0 | G30: =ROUND(G29*$C$10%,0) -> 0 | I30: =SUM(C30:H30) -> 0 | M30: e.g. Research specific materials & small-scale equipment
B31: Total overheads share | C31: =ROUND((C29+C30)*$C$11%, 0) -> 0 | E31: =ROUND((E29+E30)*$C$11%, 0) -> 0 | G31: =ROUND((G29+G30)*$C$11%, 0) -> 0 | I31: =SUM(C31:H31) -> 0 | M31: (special computer for computing, special accessories,..),
M32: user experiment costs,..
B34: Other costs | C34: 2026 | E34: =C34+1 -> 2027 | G34: =E34+1 -> 2028 | I34: Total | M34: Equipment: | P34: Mobility:
B35: Materials | C35: 0 | E35: 0 | G35: 0 | I35: =ROUND(SUM(E35,C35,G35),0) -> 0 | M35: Only large-scale equipment (> 10 k€, service life > 3 years) | P35: AoF's Mobility Allowance changed into Mobility Aid.
B36: Equipment | C36: 0 | E36: 0 | G36: 0 | I36: =ROUND(SUM(E36,C36,G36),0) -> 0 | M36: Very rarely used at CS | P36: In Aalto this means that mobilty costs are covered as real costs.
B37: Services | C37: 0 | E37: 0 | G37: 0 | I37: =ROUND(SUM(E37,C37,G37),0) -> 0 | P37: These costs may be included:
B38: Travel expenses | C38: 0 | E38: 0 | G38: 0 | I38: =ROUND(SUM(E38,C38,G38),0) -> 0 | M38: Services: | P38: - flights etc.
B39: Other costs | C39: 0 | E39: 0 | G39: 0 | I39: =ROUND(SUM(E39,C39,G39),0) -> 0 | M39: NOTE!: AoF is part of Plan-S coalition and no longer accepts | P39: - moderate living expenses (examples provided on sheet Mobility)
B40: Other costs, total | C40: =ROUND(SUM(C35:C39),0) -> 0 | E40: =ROUND(SUM(E35:E39),0) -> 0 | G40: =ROUND(SUM(G35:G39),0) -> 0 | I40: =ROUND(SUM(E40,C40,G40),0) -> 0 | M40: Open Access publication fees as direct costs. | P40: - insurance
P41: - daily allowance (>1 months stays: 30%), Note: may be excluded if total budget is puffed up
B42: Total costs | C42: =ROUND(C29+C30+C31+C40,0) -> 0 | E42: =ROUND(E29+E30+E31+E40,0) -> 0 | G42: =ROUND(G29+G30+G31+G40,0) -> 0 | I42: =ROUND(SUM(E42,C42,G42),0) -> 0 | M42: Travel expenses: | P42: - family travel expenses (for > 12 months stays)
M43: Conferences etc. | P43: All budgeted under Travel expenses.
M44: + all costs related to mobility (see blue box). | P44: Note: Do not exaggerate, use moderation.
B46: Funding | C46: 2026 | E46: =C46+1 -> 2027 | G46: =E46+1 -> 2028 | I46: Total | M46: Other costs:
B47: Own organisation | C47: =ROUND(C42*30%,0) -> 0 | E47: =ROUND(E42*30%,0) -> 0 | G47: =ROUND(G42*30%,0) -> 0 | I47: =ROUND(SUM(E47,C47,G47),0) -> 0 | M47: e.g. personal grants
B48: Foundation | C48: At our Department these are not used (except in very rare cases) | M48: Grants for international guests (see Academy call text for further information)
B49: Tekes
B50: Ministry
B51: EU
B52: Enterprise
B53: Other
B54: Other than Academy funding, total | C54: =C47 -> 0 | E54: =E47 -> 0 | G54: =G47 -> 0 | I54: =ROUND(SUM(E54,C54,G54),0) -> 0
B55: Funding contribution from other sources % | C55: =ROUND(C54*100/C42,0) -> #DIV/0! | E55: =ROUND(E54*100/E42,0) -> #DIV/0! | G55: =ROUND(G54*100/G42,0) -> #DIV/0! | I55: =ROUND(I54*100/I42,0) -> #DIV/0!
J56: max support:
B57: Academy funding contribution € | C57: =C42-C54 -> 0 | E57: =E42-E54 -> 0 | G57: =G42-G54 -> 0 | I57: =ROUND(SUM(E57,C57,G57),0) -> 0 | J57: 500000
B58: Academy funding contribution % | C58: =ROUND(C57*100/C42,0) -> #DIV/0! | E58: =ROUND(E57*100/E42,0) -> #DIV/0! | G58: =ROUND(G57*100/G42,0) -> #DIV/0! | I58: =ROUND(I57*100/I42,0) -> #DIV/0! | M58: This has to be max 70% (this sheet forces it to 70%) !!!
B60: Justification for the cost estimate: | M60: Justify all research costs, itemised by type of expenditure, in the free-text field (max 2000 characters)
B63: Name of the person issuing commitment

Sheet Budget (Partner 5)
B3: The Funding form for a Academy Project (www.aka.fi)
N4: Note that in the Academy system the separator is a period, not a comma!
B5: Funding period starts: | C5: 1.1.2026 | D5: (dd.mm.yyyy) | F5: 3 years, starting from 1.1.2026 | N5: (in this excel all figures are rounded to whole numbers)
B6: Funding period ends: | C6: 31.12.2028 | D6: (dd.mm.yyyy)
B8: Effective work hours | C8: 100 | D8: (%) | E8: = tehollinen työaika | O8: = areas to be filled in the online Academy form
B10: Indirect employee costs | C10: 46 | D10: (%) | E10: = HSK | N10: Funding: 6,5 million euros in total (HPC special call)
B11: Overheads share | C11: 75 | D11: (%) | E11: = YK | N11: up to €500,000 for individual project
B13: Other costs include VAT | C13: YES
B15: Salaries | C15: 2026 | E15: =C15+1 -> 2027 | G15: =E15+1 -> 2028 | I15: Total
A16: Choose from a list --> | B16: Postdoctoral Researcher | C16: 0 | D16: month(s) | E16: 0 | F16: month(s) | G16: 0 | H16: month(s) | K16: Max 11 months/year | N16: Make sure that a project starting/ending in the middle of a year has correct months
B17: name (optional, not in the form) | C17: 0 | D17: €/month | E17: =IF(E16,ROUND(C17*1.02,0),0) -> 0 | F17: €/month | G17: =IF(G16,ROUND(E17*1.02,0),0) -> 0 | H17: €/month | I17: =ROUND(C16*C17+E16*E17+G16*G17,0) -> 0 | N17: Fill in the monthly salary of the first year. The other years fill in automatically with an estimated raise (TES).
B19: Principal investigator | C19: 0 | D19: month(s) | E19: 0 | F19: month(s) | G19: 0 | H19: month(s)
B20: name (optional, not in the form) | C20: 0 | D20: €/month | E20: =IF(E19,ROUND(C20*1.02,0),0) -> 0 | F20: €/month | G20: =IF(G19,ROUND(E20*1.02,0),0) -> 0 | H20: €/month | I20: =ROUND(C19*C20+E19*E20+G19*G20,0) -> 0
B22: Postgraduate student | C22: 0 | D22: month(s) | E22: 0 | F22: month(s) | G22: 0 | H22: month(s)
B23: name (optional, not in the form) | C23: 0 | D23: €/month | E23: =IF(E22,ROUND(C23*1.02,0),0) -> 0 | F23: €/month | G23: =IF(G22,ROUND(E23*1.02,0),0) -> 0 | H23: €/month | I23: =ROUND(C22*C23+E22*E23+G22*G23,0) -> 0
B25: Postgraduate student | C25: 0 | D25: month(s) | E25: 0 | F25: month(s) | G25: 0 | H25: month(s)
B26: name (optional, not in the form) | C26: 0 | D26: €/month | E26: =IF(E25,ROUND(C26*1.02,0),0) -> 0 | F26: €/month | G26: =IF(G25,ROUND(E26*1.02,0),0) -> 0 | H26: €/month | I26: =ROUND(C25*C26+E25*E26+G25*G26,0) -> 0
B29: Salaries, total | C29: =C16*C17+C19*C20+C22*C23+C25*C26 -> 0 | E29: =E16*E17+E19*E20+E22*E23+E25*E26 -> 0 | G29: =G16*G17+G19*G20+G22*G23+G25*G26 -> 0 | I29: =SUM(C29:H29) -> 0 | M29: Materials:
B30: Indirect employee cost, total | C30: =ROUND(C29*$C$10%,0) -> 0 | E30: =ROUND(E29*$C$10%,0) -> 0 | G30: =ROUND(G29*$C$10%,0) -> 0 | I30: =SUM(C30:H30) -> 0 | M30: e.g. Research specific materials & small-scale equipment
B31: Total overheads share | C31: =ROUND((C29+C30)*$C$11%, 0) -> 0 | E31: =ROUND((E29+E30)*$C$11%, 0) -> 0 | G31: =ROUND((G29+G30)*$C$11%, 0) -> 0 | I31: =SUM(C31:H31) -> 0 | M31: (special computer for computing, special accessories,..),
M32: user experiment costs,..
B34: Other costs | C34: 2026 | E34: =C34+1 -> 2027 | G34: =E34+1 -> 2028 | I34: Total | M34: Equipment: | P34: Mobility:
B35: Materials | C35: 0 | E35: 0 | G35: 0 | I35: =ROUND(SUM(E35,C35,G35),0) -> 0 | M35: Only large-scale equipment (> 10 k€, service life > 3 years) | P35: AoF's Mobility Allowance changed into Mobility Aid.
B36: Equipment | C36: 0 | E36: 0 | G36: 0 | I36: =ROUND(SUM(E36,C36,G36),0) -> 0 | M36: Very rarely used at CS | P36: In Aalto this means that mobilty costs are covered as real costs.
B37: Services | C37: 0 | E37: 0 | G37: 0 | I37: =ROUND(SUM(E37,C37,G37),0) -> 0 | P37: These costs may be included:
B38: Travel expenses | C38: 0 | E38: 0 | G38: 0 | I38: =ROUND(SUM(E38,C38,G38),0) -> 0 | M38: Services: | P38: - flights etc.
B39: Other costs | C39: 0 | E39: 0 | G39: 0 | I39: =ROUND(SUM(E39,C39,G39),0) -> 0 | M39: NOTE!: AoF is part of Plan-S coalition and no longer accepts | P39: - moderate living expenses (examples provided on sheet Mobility)
B40: Other costs, total | C40: =ROUND(SUM(C35:C39),0) -> 0 | E40: =ROUND(SUM(E35:E39),0) -> 0 | G40: =ROUND(SUM(G35:G39),0) -> 0 | I40: =ROUND(SUM(E40,C40,G40),0) -> 0 | M40: Open Access publication fees as direct costs. | P40: - insurance
P41: - daily allowance (>1 months stays: 30%), Note: may be excluded if total budget is puffed up
B42: Total costs | C42: =ROUND(C29+C30+C31+C40,0) -> 0 | E42: =ROUND(E29+E30+E31+E40,0) -> 0 | G42: =ROUND(G29+G30+G31+G40,0) -> 0 | I42: =ROUND(SUM(E42,C42,G42),0) -> 0 | M42: Travel expenses: | P42: - family travel expenses (for > 12 months stays)
M43: Conferences etc. | P43: All budgeted under Travel expenses.
M44: + all costs related to mobility (see blue box). | P44: Note: Do not exaggerate, use moderation.
B46: Funding | C46: 2026 | E46: =C46+1 -> 2027 | G46: =E46+1 -> 2028 | I46: Total | M46: Other costs:
B47: Own organisation | C47: =ROUND(C42*30%,0) -> 0 | E47: =ROUND(E42*30%,0) -> 0 | G47: =ROUND(G42*30%,0) -> 0 | I47: =ROUND(SUM(E47,C47,G47),0) -> 0 | M47: e.g. personal grants
B48: Foundation | C48: At our Department these are not used (except in very rare cases) | M48: Grants for international guests (see Academy call text for further information)
B49: Tekes
B50: Ministry
B51: EU
B52: Enterprise
B53: Other
B54: Other than Academy funding, total | C54: =C47 -> 0 | E54: =E47 -> 0 | G54: =G47 -> 0 | I54: =ROUND(SUM(E54,C54,G54),0) -> 0
B55: Funding contribution from other sources % | C55: =ROUND(C54*100/C42,0) -> #DIV/0! | E55: =ROUND(E54*100/E42,0) -> #DIV/0! | G55: =ROUND(G54*100/G42,0) -> #DIV/0! | I55: =ROUND(I54*100/I42,0) -> #DIV/0!
J56: max support:
B57: Academy funding contribution € | C57: =C42-C54 -> 0 | E57: =E42-E54 -> 0 | G57: =G42-G54 -> 0 | I57: =ROUND(SUM(E57,C57,G57),0) -> 0 | J57: 500000
B58: Academy funding contribution % | C58: =ROUND(C57*100/C42,0) -> #DIV/0! | E58: =ROUND(E57*100/E42,0) -> #DIV/0! | G58: =ROUND(G57*100/G42,0) -> #DIV/0! | I58: =ROUND(I57*100/I42,0) -> #DIV/0! | M58: This has to be max 70% (this sheet forces it to 70%) !!!
B60: Justification for the cost estimate: | M60: Justify all research costs, itemised by type of expenditure, in the free-text field (max 2000 characters)
B63: Name of the person issuing commitment

Sheet Mobility
A1: THIS PAGE CONTAINS BACKGROUND INFORMATION FOR BUDGETING OF INTERNATIONAL MOBILITY (>1 month) AND CONFERENCE TRIPS.
A2: ROWS 5 TO 57 CONTAIN INFORMATION AND THERE IS BUDGETING COUNTER STARTING FROM ROW 60.
A5: MOBILITY: | G5: CONFERENCE TRIPS:
A6: AoF's Mobility Allowance changed into Mobility Aid. | G6: These costs may be included:
A7: In Aalto this means that mobilty costs are covered as real costs. | G7: - conference registration
A8: These costs may be included: | G8: - flights etc.
A9: - flights etc. | G9: - moderate living expenses
A10: - moderate living expenses | G10: - daily allowance
A11: - insurance | G11: - airport transportation (public transportation if feasible)
A12: - daily allowance (>1 months stays: 30%), Note: may be excluded if total budget is puffed up | G12: All budgeted under Travel expenses.
A13: - family travel expenses (for > 12 months stays)
A14: All budgeted under Travel expenses.
A15: Note: Do not exaggerate, use moderation.
A17: FLIGHTS: | G17: FLIGHTS:
A18: Use available travel sites to narrow down an average flight price (no business class) | G18: Use available travel sites to narrow down an average flight price (no business class)
A21: ACCOMMODATION: | G21: ACCOMMODATION:
A22: Average hotel rates in 2019 (outdated) | G22: Average hotel rates in 2019 (outdated)
D23: per day | J23: per day
A24: Expensive | D24: 300 | E24: (i.e. New York, London, San Francisco, Montreal, Milano) | G24: Expensive | J24: 300 | K24: (i.e. New York, London, San Francisco, Montreal, Milano)
A25: Average priced | D25: 120 | E25: (i.e. Western Europe (Munich, Barcelona, Brussels), other USA) | G25: Average priced | J25: 120 | K25: (i.e. Western Europe (Munich, Barcelona, Brussels), other USA)
A26: Low-priced | D26: 80 | E26: (i.e. Eastern Europe, South America) | G26: Low-priced | J26: 80 | K26: (i.e. Eastern Europe, South America)
A28: Average apartment rents in 2019 | G28: Average apartment rents in 2019
D29: per month | J29: per month
A30: Expensive | D30: 2100 | E30: (i.e. Amsterdam, New York, London, San Francisco) | G30: Expensive | J30: 2100 | K30: (i.e. Amsterdam, New York, London, San Francisco)
A31: Average priced | D31: 1200 | E31: (i.e. Western Europe, other USA) | G31: Average priced | J31: 1200 | K31: (i.e. Western Europe, other USA)
A32: Low-priced | D32: 600 | E32: (i.e. Eastern Europe) | G32: Low-priced | J32: 600 | K32: (i.e. Eastern Europe)
A35: DAILY ALLOWANCE: | G35: DAILY ALLOWANCE:
A36: Full daily allowances are paid for shorter trips and 30% allowances for > 30 day trips. | G36: Full daily allowances are paid for shorter trips and 30% allowances for > 30 day trips.
A38: See per diems (daily allowances) payable for business travel outside Finland per country/area (§13): | G38: See per diems (daily allowances) payable for business travel outside Finland per country/area (§13):
A39: https://www.vero.fi/en/detailed-guidance/decisions/47405/tax-exempt-allowances-in-2023-for-business-travel/ | G39: https://www.vero.fi/en/detailed-guidance/decisions/47405/tax-exempt-allowances-in-2023-for-business-travel/
A40: https://www.vero.fi/syventavat-vero-ohjeet/paatokset/47405/verohallinnon-paatos-verovapaista-matkakustannusten-korvauksista-vuonna-2023/ | G40: https://www.vero.fi/syventavat-vero-ohjeet/paatokset/47405/verohallinnon-paatos-verovapaista-matkakustannusten-korvauksista-vuonna-2023/
A43: OTHER COSTS: | G43: OTHER COSTS:
A44: Other acceptable costs include: | E44: transportation to/from airport | G44: Other acceptable costs include: | K44: transportation to/from airport
E45: visa costs | K45: visa costs
E46: vaccinations (malaria, etc., if required) | K46: vaccinations (malaria, etc., if required)
E47: conference registration (appr. 200 - 900 €) | K47: conference registration (appr. 200 - 900 €)
A49: NOT ALLOWED: | G49: NOT ALLOWED:
A50: Public transportation or other commute to/back to work/study place in location | G50: Public transportation or other commute to/back to work/study place in location
G51: Family travel expenses
G52: Insurance
A54: INSURANCE (for longer stays):
A55: Employees | D55: 3.364 | E55: €/day
A56: Spouses and children | D56: 4.03 | E56: €/day
A57: War risk areas | D57: 7.26 | E57: €/day
A60: Mobility budgeting help (fill in the yellow fields when applicable) | G60: Conference trip budgeting help (fill in the yellow fields when applicable)
A61: Location 1: | B61: Amsterdam | G61: Conference 1: | H61: Amsterdam
A62: Travel days | D62: =D63*30 -> 30 | G62: Travel days | J62: 5
A63: Travel months | D63: 1
A65: Flights | D65: 250 | G65: Flights | J65: 250
A66: Accommodation | B66: per month | C66: 1200 | D66: =C66*D63 -> 1200 | G66: Accommodation | H66: per day | I66: 200 | J66: =I66*J62 -> 1000
A67: Daily allowance | B67: per day | C67: 70 | D67: =C67*D62*30% -> 630 | G67: Daily allowance | H67: per day | I67: 70 | J67: =I67*J62 -> 350
A68: Taxi | D68: 100 | G68: Taxi | J68: 100
A69: Public transportation | G69: Public transportation
A70: Other costs | G70: Other costs
A71: Insurance | D71: =D62*D27 -> 0 | G71: Conference registration | J71: 600
C72: total | D72: =SUM(D65:D71) -> 2180 | E72: Budget this to the correct year under "Travel expenses" | I72: total | J72: =SUM(J65:J71) -> 2300 | K72: Budget this to the correct year under "Travel expenses"
A75: Location 2: | G75: Conference 2:
A76: Travel days | D76: =D77*30 -> 0 | G76: Travel days
A77: Travel months
A79: Flights | G79: Flights
A80: Accommodation | B80: per month | D80: =C80*D77 -> 0 | G80: Accommodation | H80: per day | J80: =I80*J76 -> 0
A81: Daily allowance | B81: per day | D81: =C81*D76*30% -> 0 | G81: Daily allowance | H81: per day | J81: =I81*J76 -> 0
A82: Taxi | G82: Taxi
A83: Public transportation | G83: Public transportation
A84: Other costs | G84: Other costs
A85: Insurance | D85: =D76*D55 -> 0 | G85: Conference registration
C86: total | D86: =SUM(D79:D85) -> 0 | E86: Budget this to the correct year under "Travel expenses" | I86: total | J86: =SUM(J79:J85) -> 0 | K86: Budget this to the correct year under "Travel expenses"

Sheet Sheet2
B2: Postgraduate student
B3: Postdoctoral Researcher
B4: Researcher
B5: Professor
B6: Assisting personnel
B7: Principal investigator
